{
    "feature_name": "lua55-reference-manual-ja",
    "created_at": "2026-01-29T00:00:00Z",
    "updated_at": "2026-01-29T15:30:00Z",
    "language": "ja",
    "phase": "design-validated",
    "approvals": {
        "requirements": {
            "generated": true,
            "approved": true
        },
        "design": {
            "generated": true,
            "approved": false,
            "validated": true,
            "validation_result": "GO_CONDITIONAL"
        },
        "tasks": {
            "generated": false,
            "approved": false
        }
    },
    "ready_for_implementation": false
}