{
    "feature_name": "lua-api-implementation-investigation",
    "created_at": "2026-01-28T00:00:00Z",
    "updated_at": "2026-01-28T12:00:00Z",
    "language": "ja",
    "phase": "completed",
    "approvals": {
        "requirements": {
            "generated": true,
            "approved": true
        },
        "design": {
            "generated": false,
            "approved": false
        },
        "tasks": {
            "generated": false,
            "approved": false
        }
    },
    "ready_for_implementation": false,
    "notes": "調査仕様のため、調査レポートをもって完了とする"
}