{
    "feature_name": "pasta-lua-startup-sequence",
    "created_at": "2026-01-10T00:00:00Z",
    "updated_at": "2026-01-10T12:00:00Z",
    "language": "ja",
    "phase": "design-generated",
    "approvals": {
        "requirements": {
            "generated": true,
            "approved": true
        },
        "design": {
            "generated": true,
            "approved": false
        },
        "tasks": {
            "generated": false,
            "approved": false
        }
    },
    "ready_for_implementation": false,
    "discussions": [
        {
            "id": 1,
            "date": "2026-01-10",
            "topic": "トランスパイル結果のロード方法（Requirement 4.3実装詳細）",
            "decision": "Option B（メモリ直接exec）を採用。キャッシュファイルはデバッグ用途のみ。",
            "rationale": "Requirements 3.5/3.8によりキャッシュ再利用しない設計のため、mlua::Lua::load()でメモリ上のバイト列から直接実行する方式が適切。将来キャッシュ再利用が必要になった場合は変更可能な設計を維持。"
        }
    ]
}